{
  "id": "aae02b6c-9b43-44f5-8326-f43b78ebb509",
  "prevId": "00000000-0000-0000-0000-000000000000",
  "version": "7",
  "dialect": "postgresql",
  "tables": {
    "public.accounts": {
      "name": "accounts",
      "schema": "",
      "columns": {
        "id": {
          "name": "id",
          "type": "integer",
          "primaryKey": true,
          "notNull": true,
          "identity": {
            "type": "always",
            "name": "accounts_id_seq",
            "schema": "public",
            "increment": "1",
            "startWith": "1",
            "minValue": "1",
            "maxValue": "2147483647",
            "cache": "1",
            "cycle": false
          }
        },
        "user_id": {
          "name": "user_id",
          "type": "integer",
          "primaryKey": false,
          "notNull": true
        },
        "account_number": {
          "name": "account_number",
          "type": "varchar(11)",
          "primaryKey": false,
          "notNull": true
        },
        "account_type": {
          "name": "account_type",
          "type": "account_type",
          "typeSchema": "public",
          "primaryKey": false,
          "notNull": true
        },
        "balance": {
          "name": "balance",
          "type": "bigint",
          "primaryKey": false,
          "notNull": true
        },
        "account_holder": {
          "name": "account_holder",
          "type": "varchar(255)",
          "primaryKey": false,
          "notNull": true
        },
        "created_at": {
          "name": "created_at",
          "type": "timestamp with time zone",
          "primaryKey": false,
          "notNull": true,
          "default": "now()"
        }
      },
      "indexes": {},
      "foreignKeys": {
        "accounts_user_id_users_id_fk": {
          "name": "accounts_user_id_users_id_fk",
          "tableFrom": "accounts",
          "tableTo": "users",
          "columnsFrom": [
            "user_id"
          ],
          "columnsTo": [
            "id"
          ],
          "onDelete": "no action",
          "onUpdate": "no action"
        }
      },
      "compositePrimaryKeys": {},
      "uniqueConstraints": {
        "accounts_accountNumber_unique": {
          "name": "accounts_accountNumber_unique",
          "nullsNotDistinct": false,
          "columns": [
            "account_number"
          ]
        }
      },
      "policies": {},
      "checkConstraints": {},
      "isRLSEnabled": false
    },
    "public.transactions": {
      "name": "transactions",
      "schema": "",
      "columns": {
        "id": {
          "name": "id",
          "type": "integer",
          "primaryKey": true,
          "notNull": true,
          "identity": {
            "type": "always",
            "name": "transactions_id_seq",
            "schema": "public",
            "increment": "1",
            "startWith": "1",
            "minValue": "1",
            "maxValue": "2147483647",
            "cache": "1",
            "cycle": false
          }
        },
        "account_id": {
          "name": "account_id",
          "type": "integer",
          "primaryKey": false,
          "notNull": true
        },
        "type": {
          "name": "type",
          "type": "transaction_type",
          "typeSchema": "public",
          "primaryKey": false,
          "notNull": true
        },
        "direction": {
          "name": "direction",
          "type": "transaction_direction",
          "typeSchema": "public",
          "primaryKey": false,
          "notNull": true
        },
        "amount": {
          "name": "amount",
          "type": "bigint",
          "primaryKey": false,
          "notNull": true
        },
        "description": {
          "name": "description",
          "type": "text",
          "primaryKey": false,
          "notNull": true
        },
        "related_account_id": {
          "name": "related_account_id",
          "type": "integer",
          "primaryKey": false,
          "notNull": false
        },
        "reference": {
          "name": "reference",
          "type": "varchar(64)",
          "primaryKey": false,
          "notNull": true
        },
        "status": {
          "name": "status",
          "type": "transaction_status",
          "typeSchema": "public",
          "primaryKey": false,
          "notNull": true,
          "default": "'COMPLETED'"
        },
        "created_at": {
          "name": "created_at",
          "type": "timestamp with time zone",
          "primaryKey": false,
          "notNull": true,
          "default": "now()"
        },
        "updated_at": {
          "name": "updated_at",
          "type": "timestamp with time zone",
          "primaryKey": false,
          "notNull": true,
          "default": "now()"
        }
      },
      "indexes": {
        "transactions_account_created_idx": {
          "name": "transactions_account_created_idx",
          "columns": [
            {
              "expression": "account_id",
              "isExpression": false,
              "asc": true,
              "nulls": "last"
            },
            {
              "expression": "created_at",
              "isExpression": false,
              "asc": true,
              "nulls": "last"
            }
          ],
          "isUnique": false,
          "concurrently": false,
          "method": "btree",
          "with": {}
        },
        "transactions_reference_idx": {
          "name": "transactions_reference_idx",
          "columns": [
            {
              "expression": "reference",
              "isExpression": false,
              "asc": true,
              "nulls": "last"
            }
          ],
          "isUnique": false,
          "concurrently": false,
          "method": "btree",
          "with": {}
        }
      },
      "foreignKeys": {
        "transactions_account_id_accounts_id_fk": {
          "name": "transactions_account_id_accounts_id_fk",
          "tableFrom": "transactions",
          "tableTo": "accounts",
          "columnsFrom": [
            "account_id"
          ],
          "columnsTo": [
            "id"
          ],
          "onDelete": "no action",
          "onUpdate": "no action"
        },
        "transactions_related_account_id_accounts_id_fk": {
          "name": "transactions_related_account_id_accounts_id_fk",
          "tableFrom": "transactions",
          "tableTo": "accounts",
          "columnsFrom": [
            "related_account_id"
          ],
          "columnsTo": [
            "id"
          ],
          "onDelete": "no action",
          "onUpdate": "no action"
        }
      },
      "compositePrimaryKeys": {},
      "uniqueConstraints": {
        "transactions_reference_unique": {
          "name": "transactions_reference_unique",
          "nullsNotDistinct": false,
          "columns": [
            "reference"
          ]
        }
      },
      "policies": {},
      "checkConstraints": {},
      "isRLSEnabled": false
    },
    "public.users": {
      "name": "users",
      "schema": "",
      "columns": {
        "id": {
          "name": "id",
          "type": "integer",
          "primaryKey": true,
          "notNull": true,
          "identity": {
            "type": "always",
            "name": "users_id_seq",
            "schema": "public",
            "increment": "1",
            "startWith": "1",
            "minValue": "1",
            "maxValue": "2147483647",
            "cache": "1",
            "cycle": false
          }
        },
        "email": {
          "name": "email",
          "type": "varchar(255)",
          "primaryKey": false,
          "notNull": true
        },
        "password_hash": {
          "name": "password_hash",
          "type": "varchar(255)",
          "primaryKey": false,
          "notNull": true
        },
        "name": {
          "name": "name",
          "type": "varchar(255)",
          "primaryKey": false,
          "notNull": true
        },
        "created_at": {
          "name": "created_at",
          "type": "timestamp with time zone",
          "primaryKey": false,
          "notNull": true,
          "default": "now()"
        }
      },
      "indexes": {},
      "foreignKeys": {},
      "compositePrimaryKeys": {},
      "uniqueConstraints": {
        "users_email_unique": {
          "name": "users_email_unique",
          "nullsNotDistinct": false,
          "columns": [
            "email"
          ]
        }
      },
      "policies": {},
      "checkConstraints": {},
      "isRLSEnabled": false
    }
  },
  "enums": {
    "public.account_type": {
      "name": "account_type",
      "schema": "public",
      "values": [
        "CHECKING",
        "SAVINGS"
      ]
    },
    "public.transaction_direction": {
      "name": "transaction_direction",
      "schema": "public",
      "values": [
        "CREDIT",
        "DEBIT"
      ]
    },
    "public.transaction_status": {
      "name": "transaction_status",
      "schema": "public",
      "values": [
        "PENDING",
        "COMPLETED",
        "FAILED"
      ]
    },
    "public.transaction_type": {
      "name": "transaction_type",
      "schema": "public",
      "values": [
        "DEPOSIT",
        "WITHDRAWAL",
        "TRANSFER"
      ]
    }
  },
  "schemas": {},
  "sequences": {},
  "roles": {},
  "policies": {},
  "views": {},
  "_meta": {
    "columns": {},
    "schemas": {},
    "tables": {}
  }
}